Workbook

Sheet Long list
A1: Psyma Ibérica · Tesis B · Long list de 15 empresas por vertical bajo el paraguas ESOMAR (España)
A2: Celdas amarillas = completar con SABI (último ejercicio disponible). Mercado: Insights + Analytics España 2024 (1.452 M€).
A4: # | B4: Bloque (tesis B) | C4: Subactividad | D4: Empresa | E4: Sede | F4: Perfil | G4: Propiedad / accionista | H4: Actividad | I4: Qué aporta a Psyma | J4: Rol en la tesis | K4: Prioridad | L4: Top 5 del bloque | M4: Web | N4: Facturación (M€) | O4: EBITDA (M€) | P4: Empleados | Q4: Año dato
A5: 1 | B5: Bloque 1 · Otros sectores | C5: Consumo y retail | D5: Instituto DYM | E5: Madrid | F5: Independiente nacional | G5: Independiente; fundado en 1962 | H5: Instituto full-service ad hoc (cuanti y cuali); 49 empleados en 2024; socio de I+A España | I5: Cartera de gran consumo y capacidad de campo; tamaño asumible para una primera compra | J5: Target build-up | K5: A | L5: Sí | M5: institutodym.es
A6: 2 | B6: Bloque 1 · Otros sectores | C6: Consumo y retail | D6: Ikerfel | E6: Bilbao | F6: Independiente nacional | G6: Independiente; fundado en 1976 | H6: Investigación de mercados y estrategia; +7.000 estudios; socio de I+A España | I6: Cobertura del norte de España; clientes de consumo y utilities | J6: Target build-up | K6: A | L6: Sí | M6: ikerfel.es
A7: 3 | B7: Bloque 1 · Otros sectores | C7: Consumo y retail | D7: More than Research | E7: Madrid | F7: Independiente nacional | G7: Fundador (ex Infratest, Synovate, Ipsos); fundada en 2011 | H7: Agencia multidisciplinar: marketing y publicidad, UX, pharma y social media; socio de I+A España | I7: Ya toca pharma: encaje cultural y cartera de consumo | J7: Target build-up | K7: A | L7: No | M7: moretr.com
A8: 4 | B8: Bloque 1 · Otros sectores | C8: Consumo y retail | D8: CS On Research | E8: Madrid (verificar) | F8: Independiente nacional | G8: Verificar en SABI | H8: Instituto 100% online con panel propio de +85.000 personas; 19 empleados; ISO 20252 | I8: Añade capacidad online y panel propio a Psyma | J8: Target build-up | K8: B | L8: No | M8: csonresearch.com
A9: 5 | B9: Bloque 1 · Otros sectores | C9: Consumo y retail | D9: Invymark | E9: Madrid | F9: Independiente nacional | G9: Verificar en SABI | H9: Investigación ad hoc y trackings para gran consumo y medios | I9: Clientes de gran consumo | J9: Target build-up | K9: C | L9: No | M9: invymark.com
A10: 6 | B10: Bloque 1 · Otros sectores | C10: Financiero / telco / B2B | D10: IO Investigación | E10: Madrid | F10: Independiente nacional | G10: Independiente | H10: Mayor instituto independiente español: telco, electrónica de consumo, banca; panel Sondea y mystery shopping | I10: Escala y cartera en telco y finanzas (ya en el deck) | J10: Target build-up | K10: A | L10: Sí | M10: ioinvestigacion.com
A11: 7 | B11: Bloque 1 · Otros sectores | C11: Financiero / telco / B2B | D11: Gizaker | E11: Bilbao | F11: Independiente nacional | G11: Verificar en SABI | H11: Investigación social y de mercados para empresas B2B y administraciones del País Vasco | I11: Complemento regional a Ikerfel | J11: Target build-up | K11: C | L11: No | M11: gizaker.com
A12: 8 | B12: Bloque 1 · Otros sectores | C12: Financiero / telco / B2B | D12: Opinòmetre | E12: Barcelona | F12: Independiente nacional | G12: Verificar en SABI | H12: Investigación de mercados y opinión en Cataluña; B2B y sector público | I12: Presencia en Cataluña | J12: Target build-up | K12: C | L12: No | M12: opinometre.com
A13: 9 | B13: Bloque 1 · Otros sectores | C13: Opinión y sector público | D13: GAD3 | E13: Madrid | F13: Independiente nacional | G13: Independiente (Narciso Michavila) | H13: Investigación social, electoral y de opinión para medios, empresas e instituciones | I13: Marca de referencia en opinión; contratos institucionales | J13: Target build-up | K13: A | L13: Sí | M13: gad3.com
A14: 10 | B14: Bloque 1 · Otros sectores | C14: Opinión y sector público | D14: Sigma Dos | E14: Madrid | F14: Independiente nacional | G14: Verificar en SABI | H14: Encuestas electorales y de opinión; alianza con Dos30' para medir plataformas; socio de I+A España | I14: Opinión + puente hacia audiencias (bloque 2) | J14: Target build-up | K14: A | L14: Sí | M14: sigmados.com
A15: 11 | B15: Bloque 1 · Otros sectores | C15: Opinión y sector público | D15: IMOP Insights | E15: Madrid | F15: Independiente nacional | G15: Verificar en SABI | H15: Investigación social y de consumo; socio de I+A España | I15: Capacidad cuantitativa y contratos públicos recurrentes | J15: Target build-up | K15: B | L15: No | M15: imop.es
A16: 12 | B16: Bloque 1 · Otros sectores | C16: Opinión y sector público | D16: Celeste-Tel | E16: Madrid | F16: Independiente nacional | G16: Verificar en SABI | H16: Encuestas de opinión y estudios de mercado; socio de I+A España | I16: Opinión y campo telefónico | J16: Target build-up | K16: B | L16: No | M16: celeste-tel.es
... A49: 45 | B49: Bloque 3 · Tecnología e insights con IA | C49: Insights automatizados con IA | D49: Cuxtomers | E49: España | F49: Startup | G49: Verificar en SABI | H49: Clientes sintéticos con LLM para investigación | I49: Opción early-stage (participación minoritaria) | J49: Target build-up | K49: C | L49: No | M49: cuxtomers.com
A51: Prioridad: A = target prioritario (tamaño y encaje), B = add-on, C = no adquirible / benchmark. 'Verificar en SABI' = propiedad no confirmada en fuentes públicas.
A52: Criterio: solo empresas del sector insights en España (socios de I+A España o equivalentes). Fuentes: Insights + Analytics España (2024) y su directorio de empresas; prensa sectorial (elEconomista, Dircomfidencial, Webcapitalriesgo, Marketing Directo, Panorama Audiovisual); webs corporativas; análisis Afianza.

Sheet Resumen
A1: Resumen por bloque y subactividad
A3: Bloque | B3: Subactividad | C3: Nº empresas | D3: Targets | E3: Prioridad A | F3: Facturación agregada (M€)
A4: Bloque 1 · Otros sectores | B4: Consumo y retail | C4: =COUNTIFS('Long list'!$B$5:$B$49,A4,'Long list'!$C$5:$C$49,B4) | D4: =COUNTIFS('Long list'!$B$5:$B$49,A4,'Long list'!$C$5:$C$49,B4,'Long list'!$J$5:$J$49,"Target build-up") | E4: =COUNTIFS('Long list'!$B$5:$B$49,A4,'Long list'!$C$5:$C$49,B4,'Long list'!$K$5:$K$49,"A") | F4: =SUMIFS('Long list'!$N$5:$N$49,'Long list'!$B$5:$B$49,A4,'Long list'!$C$5:$C$49,B4)
A5: Bloque 1 · Otros sectores | B5: Financiero / telco / B2B | C5: =COUNTIFS('Long list'!$B$5:$B$49,A5,'Long list'!$C$5:$C$49,B5) | D5: =COUNTIFS('Long list'!$B$5:$B$49,A5,'Long list'!$C$5:$C$49,B5,'Long list'!$J$5:$J$49,"Target build-up") | E5: =COUNTIFS('Long list'!$B$5:$B$49,A5,'Long list'!$C$5:$C$49,B5,'Long list'!$K$5:$K$49,"A") | F5: =SUMIFS('Long list'!$N$5:$N$49,'Long list'!$B$5:$B$49,A5,'Long list'!$C$5:$C$49,B5)
A6: Bloque 1 · Otros sectores | B6: Opinión y sector público | C6: =COUNTIFS('Long list'!$B$5:$B$49,A6,'Long list'!$C$5:$C$49,B6) | D6: =COUNTIFS('Long list'!$B$5:$B$49,A6,'Long list'!$C$5:$C$49,B6,'Long list'!$J$5:$J$49,"Target build-up") | E6: =COUNTIFS('Long list'!$B$5:$B$49,A6,'Long list'!$C$5:$C$49,B6,'Long list'!$K$5:$K$49,"A") | F6: =SUMIFS('Long list'!$N$5:$N$49,'Long list'!$B$5:$B$49,A6,'Long list'!$C$5:$C$49,B6)
A7: Bloque 2 · Medición y dato recurrente | B7: Trackings de marca | C7: =COUNTIFS('Long list'!$B$5:$B$49,A7,'Long list'!$C$5:$C$49,B7) | D7: =COUNTIFS('Long list'!$B$5:$B$49,A7,'Long list'!$C$5:$C$49,B7,'Long list'!$J$5:$J$49,"Target build-up") | E7: =COUNTIFS('Long list'!$B$5:$B$49,A7,'Long list'!$C$5:$C$49,B7,'Long list'!$K$5:$K$49,"A") | F7: =SUMIFS('Long list'!$N$5:$N$49,'Long list'!$B$5:$B$49,A7,'Long list'!$C$5:$C$49,B7)
A8: Bloque 2 · Medición y dato recurrente | B8: Experiencia de cliente y paciente | C8: =COUNTIFS('Long list'!$B$5:$B$49,A8,'Long list'!$C$5:$C$49,B8) | D8: =COUNTIFS('Long list'!$B$5:$B$49,A8,'Long list'!$C$5:$C$49,B8,'Long list'!$J$5:$J$49,"Target build-up") | E8: =COUNTIFS('Long list'!$B$5:$B$49,A8,'Long list'!$C$5:$C$49,B8,'Long list'!$K$5:$K$49,"A") | F8: =SUMIFS('Long list'!$N$5:$N$49,'Long list'!$B$5:$B$49,A8,'Long list'!$C$5:$C$49,B8)
A9: Bloque 2 · Medición y dato recurrente | B9: Medición de audiencias | C9: =COUNTIFS('Long list'!$B$5:$B$49,A9,'Long list'!$C$5:$C$49,B9) | D9: =COUNTIFS('Long list'!$B$5:$B$49,A9,'Long list'!$C$5:$C$49,B9,'Long list'!$J$5:$J$49,"Target build-up") | E9: =COUNTIFS('Long list'!$B$5:$B$49,A9,'Long list'!$C$5:$C$49,B9,'Long list'!$K$5:$K$49,"A") | F9: =SUMIFS('Long list'!$N$5:$N$49,'Long list'!$B$5:$B$49,A9,'Long list'!$C$5:$C$49,B9)
A10: Bloque 2 · Medición y dato recurrente | B10: Consultoría estratégica | C10: =COUNTIFS('Long list'!$B$5:$B$49,A10,'Long list'!$C$5:$C$49,B10) | D10: =COUNTIFS('Long list'!$B$5:$B$49,A10,'Long list'!$C$5:$C$49,B10,'Long list'!$J$5:$J$49,"Target build-up") | E10: =COUNTIFS('Long list'!$B$5:$B$49,A10,'Long list'!$C$5:$C$49,B10,'Long list'!$K$5:$K$49,"A") | F10: =SUMIFS('Long list'!$N$5:$N$49,'Long list'!$B$5:$B$49,A10,'Long list'!$C$5:$C$49,B10)
A11: Bloque 3 · Tecnología e insights con IA | B11: Monitorización de medios | C11: =COUNTIFS('Long list'!$B$5:$B$49,A11,'Long list'!$C$5:$C$49,B11) | D11: =COUNTIFS('Long list'!$B$5:$B$49,A11,'Long list'!$C$5:$C$49,B11,'Long list'!$J$5:$J$49,"Target build-up") | E11: =COUNTIFS('Long list'!$B$5:$B$49,A11,'Long list'!$C$5:$C$49,B11,'Long list'!$K$5:$K$49,"A") | F11: =SUMIFS('Long list'!$N$5:$N$49,'Long list'!$B$5:$B$49,A11,'Long list'!$C$5:$C$49,B11)
A12: Bloque 3 · Tecnología e insights con IA | B12: Ad intelligence | C12: =COUNTIFS('Long list'!$B$5:$B$49,A12,'Long list'!$C$5:$C$49,B12) | D12: =COUNTIFS('Long list'!$B$5:$B$49,A12,'Long list'!$C$5:$C$49,B12,'Long list'!$J$5:$J$49,"Target build-up") | E12: =COUNTIFS('Long list'!$B$5:$B$49,A12,'Long list'!$C$5:$C$49,B12,'Long list'!$K$5:$K$49,"A") | F12: =SUMIFS('Long list'!$N$5:$N$49,'Long list'!$B$5:$B$49,A12,'Long list'!$C$5:$C$49,B12)
A13: Bloque 3 · Tecnología e insights con IA | B13: Software de analítica | C13: =COUNTIFS('Long list'!$B$5:$B$49,A13,'Long list'!$C$5:$C$49,B13) | D13: =COUNTIFS('Long list'!$B$5:$B$49,A13,'Long list'!$C$5:$C$49,B13,'Long list'!$J$5:$J$49,"Target build-up") | E13: =COUNTIFS('Long list'!$B$5:$B$49,A13,'Long list'!$C$5:$C$49,B13,'Long list'!$K$5:$K$49,"A") | F13: =SUMIFS('Long list'!$N$5:$N$49,'Long list'!$B$5:$B$49,A13,'Long list'!$C$5:$C$49,B13)
A14: Bloque 3 · Tecnología e insights con IA | B14: Insights automatizados con IA | C14: =COUNTIFS('Long list'!$B$5:$B$49,A14,'Long list'!$C$5:$C$49,B14) | D14: =COUNTIFS('Long list'!$B$5:$B$49,A14,'Long list'!$C$5:$C$49,B14,'Long list'!$J$5:$J$49,"Target build-up") | E14: =COUNTIFS('Long list'!$B$5:$B$49,A14,'Long list'!$C$5:$C$49,B14,'Long list'!$K$5:$K$49,"A") | F14: =SUMIFS('Long list'!$N$5:$N$49,'Long list'!$B$5:$B$49,A14,'Long list'!$C$5:$C$49,B14)
A15: Total | C15: =SUM(C4:C14) | D15: =SUM(D4:D14) | E15: =SUM(E4:E14) | F15: =SUM(F4:F14)
A17: Comprobación: 15 empresas por bloque
A18: Bloque 1 · Otros sectores | C18: =COUNTIF('Long list'!$B$5:$B$49,A18)
A19: Bloque 2 · Medición y dato recurrente | C19: =COUNTIF('Long list'!$B$5:$B$49,A19)
A20: Bloque 3 · Tecnología e insights con IA | C20: =COUNTIF('Long list'!$B$5:$B$49,A20)

Sheet Top 5 para láminas
A1: Cinco targets destacados por bloque (alimenta las láminas 31-33 del deck)
A3: Bloque 1 · Otros sectores
A4: Empresa | B4: Actividad | C4: Facturación (M€) | D4: EBITDA (M€) | E4: Qué aporta a Psyma
A5: ='Long list'!D5 | B5: ='Long list'!H5 | C5: =IF('Long list'!N5="","[PENDIENTE]",'Long list'!N5) | D5: =IF('Long list'!O5="","[PENDIENTE]",'Long list'!O5) | E5: ='Long list'!I5
A6: ='Long list'!D6 | B6: ='Long list'!H6 | C6: =IF('Long list'!N6="","[PENDIENTE]",'Long list'!N6) | D6: =IF('Long list'!O6="","[PENDIENTE]",'Long list'!O6) | E6: ='Long list'!I6
A7: ='Long list'!D10 | B7: ='Long list'!H10 | C7: =IF('Long list'!N10="","[PENDIENTE]",'Long list'!N10) | D7: =IF('Long list'!O10="","[PENDIENTE]",'Long list'!O10) | E7: ='Long list'!I10
A8: ='Long list'!D13 | B8: ='Long list'!H13 | C8: =IF('Long list'!N13="","[PENDIENTE]",'Long list'!N13) | D8: =IF('Long list'!O13="","[PENDIENTE]",'Long list'!O13) | E8: ='Long list'!I13
A9: ='Long list'!D14 | B9: ='Long list'!H14 | C9: =IF('Long list'!N14="","[PENDIENTE]",'Long list'!N14) | D9: =IF('Long list'!O14="","[PENDIENTE]",'Long list'!O14) | E9: ='Long list'!I14
A11: Bloque 2 · Medición y dato recurrente
A12: Empresa | B12: Actividad | C12: Facturación (M€) | D12: EBITDA (M€) | E12: Qué aporta a Psyma
A13: ='Long list'!D24 | B13: ='Long list'!H24 | C13: =IF('Long list'!N24="","[PENDIENTE]",'Long list'!N24) | D13: =IF('Long list'!O24="","[PENDIENTE]",'Long list'!O24) | E13: ='Long list'!I24
A14: ='Long list'!D25 | B14: ='Long list'!H25 | C14: =IF('Long list'!N25="","[PENDIENTE]",'Long list'!N25) | D14: =IF('Long list'!O25="","[PENDIENTE]",'Long list'!O25) | E14: ='Long list'!I25
A15: ='Long list'!D29 | B15: ='Long list'!H29 | C15: =IF('Long list'!N29="","[PENDIENTE]",'Long list'!N29) | D15: =IF('Long list'!O29="","[PENDIENTE]",'Long list'!O29) | E15: ='Long list'!I29
A16: ='Long list'!D30 | B16: ='Long list'!H30 | C16: =IF('Long list'!N30="","[PENDIENTE]",'Long list'!N30) | D16: =IF('Long list'!O30="","[PENDIENTE]",'Long list'!O30) | E16: ='Long list'!I30
A17: ='Long list'!D32 | B17: ='Long list'!H32 | C17: =IF('Long list'!N32="","[PENDIENTE]",'Long list'!N32) | D17: =IF('Long list'!O32="","[PENDIENTE]",'Long list'!O32) | E17: ='Long list'!I32
A19: Bloque 3 · Tecnología e insights con IA
A20: Empresa | B20: Actividad | C20: Facturación (M€) | D20: EBITDA (M€) | E20: Qué aporta a Psyma
A21: ='Long list'!D35 | B21: ='Long list'!H35 | C21: =IF('Long list'!N35="","[PENDIENTE]",'Long list'!N35) | D21: =IF('Long list'!O35="","[PENDIENTE]",'Long list'!O35) | E21: ='Long list'!I35
A22: ='Long list'!D40 | B22: ='Long list'!H40 | C22: =IF('Long list'!N40="","[PENDIENTE]",'Long list'!N40) | D22: =IF('Long list'!O40="","[PENDIENTE]",'Long list'!O40) | E22: ='Long list'!I40
A23: ='Long list'!D43 | B23: ='Long list'!H43 | C23: =IF('Long list'!N43="","[PENDIENTE]",'Long list'!N43) | D23: =IF('Long list'!O43="","[PENDIENTE]",'Long list'!O43) | E23: ='Long list'!I43
A24: ='Long list'!D44 | B24: ='Long list'!H44 | C24: =IF('Long list'!N44="","[PENDIENTE]",'Long list'!N44) | D24: =IF('Long list'!O44="","[PENDIENTE]",'Long list'!O44) | E24: ='Long list'!I44
A25: ='Long list'!D46 | B25: ='Long list'!H46 | C25: =IF('Long list'!N46="","[PENDIENTE]",'Long list'!N46) | D25: =IF('Long list'!O46="","[PENDIENTE]",'Long list'!O46) | E25: ='Long list'!I46
