Workbook

Sheet Tesis B · 15 targets
A1: Tesis B · 15 targets (penúltima lámina)
A2: Amarillo = dato a completar con SABI (último ejercicio disponible). Azul = dato introducido. Negro = fórmula.
A4: # | B4: Empresa | C4: Vertical | D4: Descripción de servicios | E4: Especialización | F4: Accionista / nota | G4: Ingresos (k€) | H4: Año dato | I4: EBITDA (k€) | J4: Margen EBITDA | K4: Clave ranking (aux.)
A5: 1 | B5: Sigma Dos | C5: Investigación de mercados | D5: Encuestas electorales y de opinión; alianza con Dos30' en audiencias | E5: Opinión pública | F5: Independiente | G5: 5868 | H5: 2024 | I5: 939 | J5: =IF(AND(ISNUMBER(G5),ISNUMBER(I5),G5<>0),I5/G5,"n.d.") | K5: =IF(AND(ISNUMBER(I5),I5>0),I5+ROW()/1000000,"")
A6: 2 | B6: Stiga CX | C6: Reporting y consultoría | D6: Medición de CX, calidad de servicio, mystery shopping y data | E6: Experiencia de cliente | F6: Independiente | G6: 8528 | H6: 2025 | I6: 740 | J6: =IF(AND(ISNUMBER(G6),ISNUMBER(I6),G6<>0),I6/G6,"n.d.") | K6: =IF(AND(ISNUMBER(I6),I6>0),I6+ROW()/1000000,"")
A7: 3 | B7: Epsilon Technologies | C7: Empresas tecnológicas | D7: Big data y analítica de redes sociales para marcas | E7: Social listening | F7: Independiente | G7: 3135 | H7: 2024 | I7: 452 | J7: =IF(AND(ISNUMBER(G7),ISNUMBER(I7),G7<>0),I7/G7,"n.d.") | K7: =IF(AND(ISNUMBER(I7),I7>0),I7+ROW()/1000000,"")
A8: 4 | B8: InfoAdex | C8: Empresas tecnológicas | D8: Referencia en el control de la inversión publicitaria en España | E8: Ad intelligence | F8: Verificar accionista | G8: 3740 | H8: 2025 | I8: 345 | J8: =IF(AND(ISNUMBER(G8),ISNUMBER(I8),G8<>0),I8/G8,"n.d.") | K8: =IF(AND(ISNUMBER(I8),I8>0),I8+ROW()/1000000,"")
A9: 5 | B9: We Are Testers | C9: Empresas tecnológicas | D9: Plataforma de UX research con panel propio de testers | E9: UX research y panel | F9: Independiente | G9: 1292 | H9: 2024 | I9: 292 | J9: =IF(AND(ISNUMBER(G9),ISNUMBER(I9),G9<>0),I9/G9,"n.d.") | K9: =IF(AND(ISNUMBER(I9),I9>0),I9+ROW()/1000000,"")
A10: 6 | B10: Dos30' | C10: Reporting y consultoría | D10: Análisis de audiencias de TV y plataformas; alianza con Sigma Dos | E10: Medición de audiencias | F10: Sociedad: Breaking Ratings SL | G10: 736 | H10: 2025 | I10: 197 | J10: =IF(AND(ISNUMBER(G10),ISNUMBER(I10),G10<>0),I10/G10,"n.d.") | K10: =IF(AND(ISNUMBER(I10),I10>0),I10+ROW()/1000000,"")
A11: 7 | B11: GAD3 | C11: Investigación de mercados | D11: Investigación social, electoral y de opinión para medios e instituciones | E11: Opinión e instituciones | F11: Independiente | G11: 1958 | H11: 2024 | I11: 161 | J11: =IF(AND(ISNUMBER(G11),ISNUMBER(I11),G11<>0),I11/G11,"n.d.") | K11: =IF(AND(ISNUMBER(I11),I11>0),I11+ROW()/1000000,"")
A12: 8 | B12: Auditmedia Group | C12: Empresas tecnológicas | D12: Clipping y análisis en prensa, digital, audiovisual y redes | E12: Monitorización de medios | F12: Sociedad: Auditoría de Medios SL | G12: 2876 | H12: 2025 | I12: 103 | J12: =IF(AND(ISNUMBER(G12),ISNUMBER(I12),G12<>0),I12/G12,"n.d.") | K12: =IF(AND(ISNUMBER(I12),I12>0),I12+ROW()/1000000,"")
A13: 9 | B13: IMOP Insights | C13: Investigación de mercados | D13: Investigación social y de consumo; socio de I+A España | E13: Social y consumo | F13: Independiente | G13: 2699 | H13: 2024 | I13: 70 | J13: =IF(AND(ISNUMBER(G13),ISNUMBER(I13),G13<>0),I13/G13,"n.d.") | K13: =IF(AND(ISNUMBER(I13),I13>0),I13+ROW()/1000000,"")
A14: 10 | B14: Random Strategy | C14: Reporting y consultoría | D14: Investigación y consultoría con trackings continuos y equipo senior | E14: Trackings de marca | F14: Capital de sus directivos | G14: 1356 | H14: 2024 | I14: 69 | J14: =IF(AND(ISNUMBER(G14),ISNUMBER(I14),G14<>0),I14/G14,"n.d.") | K14: =IF(AND(ISNUMBER(I14),I14>0),I14+ROW()/1000000,"")
A15: 11 | B15: Ikerfel | C15: Investigación de mercados | D15: Investigación de mercados y estrategia; más de 7.000 estudios | E15: Consumo y utilities | F15: Independiente | G15: 4335 | H15: 2025 | I15: 13 | J15: =IF(AND(ISNUMBER(G15),ISNUMBER(I15),G15<>0),I15/G15,"n.d.") | K15: =IF(AND(ISNUMBER(I15),I15>0),I15+ROW()/1000000,"")
A16: 12 | B16: IO Investigación | C16: Investigación de mercados | D16: Mayor instituto independiente español; telco, electrónica de consumo y banca | E16: Telco y finanzas | F16: Independiente · EBITDA negativo | G16: 9903 | H16: 2024 | I16: -82 | J16: =IF(AND(ISNUMBER(G16),ISNUMBER(I16),G16<>0),I16/G16,"n.d.") | K16: =IF(AND(ISNUMBER(I16),I16>0),I16+ROW()/1000000,"")
A17: 13 | B17: Análisis e Investigación | C17: Reporting y consultoría | D17: Investigación y reporting de reputación corporativa (Merco) | E17: Reputación corporativa | F17: Sin datos en SABI (n.d.) | J17: =IF(AND(ISNUMBER(G17),ISNUMBER(I17),G17<>0),I17/G17,"n.d.") | K17: =IF(AND(ISNUMBER(I17),I17>0),I17+ROW()/1000000,"")
A18: 14 | B18: IEXP | C18: Reporting y consultoría | D18: Medición y consultoría de experiencia de paciente | E18: Experiencia de paciente | F18: Sin datos en SABI (n.d.) | J18: =IF(AND(ISNUMBER(G18),ISNUMBER(I18),G18<>0),I18/G18,"n.d.") | K18: =IF(AND(ISNUMBER(I18),I18>0),I18+ROW()/1000000,"")
A19: 15 | B19: Arce Media | C19: Empresas tecnológicas | D19: Control de la actividad publicitaria | E19: Ad intelligence | F19: Datos SABI pendientes | J19: =IF(AND(ISNUMBER(G19),ISNUMBER(I19),G19<>0),I19/G19,"n.d.") | K19: =IF(AND(ISNUMBER(I19),I19>0),I19+ROW()/1000000,"")
B20: Total (con dato) | G20: =SUM(G5:G19) | I20: =SUM(I5:I19) | J20: =IF(G20<>0,I20/G20,"n.d.")

Sheet Tesis A · 15 targets
A1: Tesis A · 15 targets fuera de investigación de mercados (penúltima lámina)
A2: Amarillo = dato a completar con SABI (último ejercicio disponible). Azul = dato introducido. Negro = fórmula.
A4: # | B4: Empresa | C4: Vertical | D4: Descripción de servicios | E4: Especialización | F4: Accionista / nota | G4: Ingresos (k€) | H4: Año dato | I4: EBITDA (k€) | J4: Margen EBITDA | K4: Clave ranking (aux.)
A5: 1 | B5: Hygeia Consulting | C5: 2 · Estrategia y consultoría | D5: Consultoría e investigación aplicada en gestión y evaluación de servicios y políticas sanitarias | E5: Estrategia en salud | F5: Independiente (verificar) · Madrid | J5: =IF(AND(ISNUMBER(G5),ISNUMBER(I5),G5<>0),I5/G5,"n.d.") | K5: =IF(AND(ISNUMBER(I5),I5>0),I5+ROW()/1000000,"")
A6: 2 | B6: Luzán 5 Health Consulting | C6: 2 · Estrategia y consultoría | D6: Consultoría en salud y formación médica; empresa familiar desde 1982 | E6: Consultoría + formación | F6: Familiar · Madrid | J6: =IF(AND(ISNUMBER(G6),ISNUMBER(I6),G6<>0),I6/G6,"n.d.") | K6: =IF(AND(ISNUMBER(I6),I6>0),I6+ROW()/1000000,"")
A7: 3 | B7: Mediformplus | C7: 2 · Estrategia y consultoría | D7: Apoyo a la industria farmacéutica en estrategia comercial y trade marketing | E7: Estrategia comercial pharma | F7: Verificar | J7: =IF(AND(ISNUMBER(G7),ISNUMBER(I7),G7<>0),I7/G7,"n.d.") | K7: =IF(AND(ISNUMBER(I7),I7>0),I7+ROW()/1000000,"")
A8: 4 | B8: PORIB | C8: 3 · Evidencia (HEOR y RWE) | D8: HEOR, bioestadística, economía de la salud y market access; desde 2004 | E8: HEOR y market access | F8: Independiente · Pozuelo (Madrid) | J8: =IF(AND(ISNUMBER(G8),ISNUMBER(I8),G8<>0),I8/G8,"n.d.") | K8: =IF(AND(ISNUMBER(I8),I8>0),I8+ROW()/1000000,"")
A9: 5 | B9: Axentiva Solutions | C9: 3 · Evidencia (HEOR y RWE) | D9: Modelización HEOR y market access; Top 10 HEOR Europa 2023 | E9: HEOR | F9: Fundador · Barcelona | J9: =IF(AND(ISNUMBER(G9),ISNUMBER(I9),G9<>0),I9/G9,"n.d.") | K9: =IF(AND(ISNUMBER(I9),I9>0),I9+ROW()/1000000,"")
A10: 6 | B10: OXON Epidemiology | C10: 3 · Evidencia (HEOR y RWE) | D10: CRO de evidencia en vida real: estudios observacionales y farmacoepidemiología | E10: RWE | F10: Verificar (posible vínculo Syneos) · Madrid | J10: =IF(AND(ISNUMBER(G10),ISNUMBER(I10),G10<>0),I10/G10,"n.d.") | K10: =IF(AND(ISNUMBER(I10),I10>0),I10+ROW()/1000000,"")
A11: 7 | B11: Medical Media | C11: 5 · Comunicación médica | D11: Agencia médica, productora audiovisual y cursos médicos; desde 2004 | E11: Contenido audiovisual médico | F11: Verificar | J11: =IF(AND(ISNUMBER(G11),ISNUMBER(I11),G11<>0),I11/G11,"n.d.") | K11: =IF(AND(ISNUMBER(I11),I11>0),I11+ROW()/1000000,"")
A12: 8 | B12: Get Access Consulting | C12: 4 · Acceso y pricing | D12: Precio y reembolso, acceso temprano y market access regional | E12: Pricing y reembolso | F12: Independiente (verificar) | J12: =IF(AND(ISNUMBER(G12),ISNUMBER(I12),G12<>0),I12/G12,"n.d.") | K12: =IF(AND(ISNUMBER(I12),I12>0),I12+ROW()/1000000,"")
A13: 9 | B13: RCAPharma | C13: 4 · Acceso y pricing | D13: Asesoría regulatoria, farmacovigilancia y acceso al mercado; desde 1991 | E13: Acceso + regulatorio | F13: Independiente (verificar) · Madrid | J13: =IF(AND(ISNUMBER(G13),ISNUMBER(I13),G13<>0),I13/G13,"n.d.") | K13: =IF(AND(ISNUMBER(I13),I13>0),I13+ROW()/1000000,"")
A14: 10 | B14: Ergon | C14: 5 · Comunicación médica | D14: Comunicación médica y edición científica para la industria farmacéutica | E14: Contenido científico | F14: Independiente (verificar) · Madrid | J14: =IF(AND(ISNUMBER(G14),ISNUMBER(I14),G14<>0),I14/G14,"n.d.") | K14: =IF(AND(ISNUMBER(I14),I14>0),I14+ROW()/1000000,"")
A15: 11 | B15: Doctaforum | C15: 5 · Comunicación médica | D15: Comunicación en salud, consultoría científica y eventos médicos; +50 empleados | E15: Eventos y congresos médicos | F15: Independiente (verificar) · Madrid | J15: =IF(AND(ISNUMBER(G15),ISNUMBER(I15),G15<>0),I15/G15,"n.d.") | K15: =IF(AND(ISNUMBER(I15),I15>0),I15+ROW()/1000000,"")
A16: 12 | B16: Content Ed Net | C16: 5 · Comunicación médica | D16: Redacción médica y comunicación científica | E16: Medical writing | F16: Verificar · Madrid | J16: =IF(AND(ISNUMBER(G16),ISNUMBER(I16),G16<>0),I16/G16,"n.d.") | K16: =IF(AND(ISNUMBER(I16),I16>0),I16+ROW()/1000000,"")
... A19: 15 | B19: Esmon Pharma | C19: 5 · Comunicación médica | D19: Editorial y comunicación médica | E19: Comunicación médica | F19: Verificar | J19: =IF(AND(ISNUMBER(G19),ISNUMBER(I19),G19<>0),I19/G19,"n.d.") | K19: =IF(AND(ISNUMBER(I19),I19>0),I19+ROW()/1000000,"")
B20: Total (con dato) | G20: =SUM(G5:G19) | I20: =SUM(I5:I19) | J20: =IF(G20<>0,I20/G20,"n.d.")

Sheet Tesis B · Top 5
A1: Tesis B · Top 5 que maximiza el EV (última lámina)
A2: Fuente: SABI (último ejercicio disponible por empresa); webs corporativas. Análisis Afianza.
A4: # | B4: Empresa | C4: Vertical | D4: Descripción de servicios | E4: Especialización | F4: Ingresos (k€) | G4: Año dato | H4: EBITDA (k€) | I4: Margen EBITDA
A5: 1 | B5: =IFERROR(INDEX('Tesis B · 15 targets'!$B$5:$B$19,MATCH(LARGE('Tesis B · 15 targets'!$K$5:$K$19,1),'Tesis B · 15 targets'!$K$5:$K$19,0)),"[SABI pendiente]") | C5: =IFERROR(INDEX('Tesis B · 15 targets'!$C$5:$C$19,MATCH(LARGE('Tesis B · 15 targets'!$K$5:$K$19,1),'Tesis B · 15 targets'!$K$5:$K$19,0)),"[SABI pendiente]") | D5: =IFERROR(INDEX('Tesis B · 15 targets'!$D$5:$D$19,MATCH(LARGE('Tesis B · 15 targets'!$K$5:$K$19,1),'Tesis B · 15 targets'!$K$5:$K$19,0)),"[SABI pendiente]") | E5: =IFERROR(INDEX('Tesis B · 15 targets'!$E$5:$E$19,MATCH(LARGE('Tesis B · 15 targets'!$K$5:$K$19,1),'Tesis B · 15 targets'!$K$5:$K$19,0)),"[SABI pendiente]") | F5: =IFERROR(INDEX('Tesis B · 15 targets'!$G$5:$G$19,MATCH(LARGE('Tesis B · 15 targets'!$K$5:$K$19,1),'Tesis B · 15 targets'!$K$5:$K$19,0)),"[SABI pendiente]") | G5: =IFERROR(INDEX('Tesis B · 15 targets'!$H$5:$H$19,MATCH(LARGE('Tesis B · 15 targets'!$K$5:$K$19,1),'Tesis B · 15 targets'!$K$5:$K$19,0)),"[SABI pendiente]") | H5: =IFERROR(INDEX('Tesis B · 15 targets'!$I$5:$I$19,MATCH(LARGE('Tesis B · 15 targets'!$K$5:$K$19,1),'Tesis B · 15 targets'!$K$5:$K$19,0)),"[SABI pendiente]") | I5: =IFERROR(H5/F5,"n.d.")
A6: 2 | B6: =IFERROR(INDEX('Tesis B · 15 targets'!$B$5:$B$19,MATCH(LARGE('Tesis B · 15 targets'!$K$5:$K$19,2),'Tesis B · 15 targets'!$K$5:$K$19,0)),"[SABI pendiente]") | C6: =IFERROR(INDEX('Tesis B · 15 targets'!$C$5:$C$19,MATCH(LARGE('Tesis B · 15 targets'!$K$5:$K$19,2),'Tesis B · 15 targets'!$K$5:$K$19,0)),"[SABI pendiente]") | D6: =IFERROR(INDEX('Tesis B · 15 targets'!$D$5:$D$19,MATCH(LARGE('Tesis B · 15 targets'!$K$5:$K$19,2),'Tesis B · 15 targets'!$K$5:$K$19,0)),"[SABI pendiente]") | E6: =IFERROR(INDEX('Tesis B · 15 targets'!$E$5:$E$19,MATCH(LARGE('Tesis B · 15 targets'!$K$5:$K$19,2),'Tesis B · 15 targets'!$K$5:$K$19,0)),"[SABI pendiente]") | F6: =IFERROR(INDEX('Tesis B · 15 targets'!$G$5:$G$19,MATCH(LARGE('Tesis B · 15 targets'!$K$5:$K$19,2),'Tesis B · 15 targets'!$K$5:$K$19,0)),"[SABI pendiente]") | G6: =IFERROR(INDEX('Tesis B · 15 targets'!$H$5:$H$19,MATCH(LARGE('Tesis B · 15 targets'!$K$5:$K$19,2),'Tesis B · 15 targets'!$K$5:$K$19,0)),"[SABI pendiente]") | H6: =IFERROR(INDEX('Tesis B · 15 targets'!$I$5:$I$19,MATCH(LARGE('Tesis B · 15 targets'!$K$5:$K$19,2),'Tesis B · 15 targets'!$K$5:$K$19,0)),"[SABI pendiente]") | I6: =IFERROR(H6/F6,"n.d.")
A7: 3 | B7: =IFERROR(INDEX('Tesis B · 15 targets'!$B$5:$B$19,MATCH(LARGE('Tesis B · 15 targets'!$K$5:$K$19,3),'Tesis B · 15 targets'!$K$5:$K$19,0)),"[SABI pendiente]") | C7: =IFERROR(INDEX('Tesis B · 15 targets'!$C$5:$C$19,MATCH(LARGE('Tesis B · 15 targets'!$K$5:$K$19,3),'Tesis B · 15 targets'!$K$5:$K$19,0)),"[SABI pendiente]") | D7: =IFERROR(INDEX('Tesis B · 15 targets'!$D$5:$D$19,MATCH(LARGE('Tesis B · 15 targets'!$K$5:$K$19,3),'Tesis B · 15 targets'!$K$5:$K$19,0)),"[SABI pendiente]") | E7: =IFERROR(INDEX('Tesis B · 15 targets'!$E$5:$E$19,MATCH(LARGE('Tesis B · 15 targets'!$K$5:$K$19,3),'Tesis B · 15 targets'!$K$5:$K$19,0)),"[SABI pendiente]") | F7: =IFERROR(INDEX('Tesis B · 15 targets'!$G$5:$G$19,MATCH(LARGE('Tesis B · 15 targets'!$K$5:$K$19,3),'Tesis B · 15 targets'!$K$5:$K$19,0)),"[SABI pendiente]") | G7: =IFERROR(INDEX('Tesis B · 15 targets'!$H$5:$H$19,MATCH(LARGE('Tesis B · 15 targets'!$K$5:$K$19,3),'Tesis B · 15 targets'!$K$5:$K$19,0)),"[SABI pendiente]") | H7: =IFERROR(INDEX('Tesis B · 15 targets'!$I$5:$I$19,MATCH(LARGE('Tesis B · 15 targets'!$K$5:$K$19,3),'Tesis B · 15 targets'!$K$5:$K$19,0)),"[SABI pendiente]") | I7: =IFERROR(H7/F7,"n.d.")
A8: 4 | B8: =IFERROR(INDEX('Tesis B · 15 targets'!$B$5:$B$19,MATCH(LARGE('Tesis B · 15 targets'!$K$5:$K$19,4),'Tesis B · 15 targets'!$K$5:$K$19,0)),"[SABI pendiente]") | C8: =IFERROR(INDEX('Tesis B · 15 targets'!$C$5:$C$19,MATCH(LARGE('Tesis B · 15 targets'!$K$5:$K$19,4),'Tesis B · 15 targets'!$K$5:$K$19,0)),"[SABI pendiente]") | D8: =IFERROR(INDEX('Tesis B · 15 targets'!$D$5:$D$19,MATCH(LARGE('Tesis B · 15 targets'!$K$5:$K$19,4),'Tesis B · 15 targets'!$K$5:$K$19,0)),"[SABI pendiente]") | E8: =IFERROR(INDEX('Tesis B · 15 targets'!$E$5:$E$19,MATCH(LARGE('Tesis B · 15 targets'!$K$5:$K$19,4),'Tesis B · 15 targets'!$K$5:$K$19,0)),"[SABI pendiente]") | F8: =IFERROR(INDEX('Tesis B · 15 targets'!$G$5:$G$19,MATCH(LARGE('Tesis B · 15 targets'!$K$5:$K$19,4),'Tesis B · 15 targets'!$K$5:$K$19,0)),"[SABI pendiente]") | G8: =IFERROR(INDEX('Tesis B · 15 targets'!$H$5:$H$19,MATCH(LARGE('Tesis B · 15 targets'!$K$5:$K$19,4),'Tesis B · 15 targets'!$K$5:$K$19,0)),"[SABI pendiente]") | H8: =IFERROR(INDEX('Tesis B · 15 targets'!$I$5:$I$19,MATCH(LARGE('Tesis B · 15 targets'!$K$5:$K$19,4),'Tesis B · 15 targets'!$K$5:$K$19,0)),"[SABI pendiente]") | I8: =IFERROR(H8/F8,"n.d.")
A9: 5 | B9: =IFERROR(INDEX('Tesis B · 15 targets'!$B$5:$B$19,MATCH(LARGE('Tesis B · 15 targets'!$K$5:$K$19,5),'Tesis B · 15 targets'!$K$5:$K$19,0)),"[SABI pendiente]") | C9: =IFERROR(INDEX('Tesis B · 15 targets'!$C$5:$C$19,MATCH(LARGE('Tesis B · 15 targets'!$K$5:$K$19,5),'Tesis B · 15 targets'!$K$5:$K$19,0)),"[SABI pendiente]") | D9: =IFERROR(INDEX('Tesis B · 15 targets'!$D$5:$D$19,MATCH(LARGE('Tesis B · 15 targets'!$K$5:$K$19,5),'Tesis B · 15 targets'!$K$5:$K$19,0)),"[SABI pendiente]") | E9: =IFERROR(INDEX('Tesis B · 15 targets'!$E$5:$E$19,MATCH(LARGE('Tesis B · 15 targets'!$K$5:$K$19,5),'Tesis B · 15 targets'!$K$5:$K$19,0)),"[SABI pendiente]") | F9: =IFERROR(INDEX('Tesis B · 15 targets'!$G$5:$G$19,MATCH(LARGE('Tesis B · 15 targets'!$K$5:$K$19,5),'Tesis B · 15 targets'!$K$5:$K$19,0)),"[SABI pendiente]") | G9: =IFERROR(INDEX('Tesis B · 15 targets'!$H$5:$H$19,MATCH(LARGE('Tesis B · 15 targets'!$K$5:$K$19,5),'Tesis B · 15 targets'!$K$5:$K$19,0)),"[SABI pendiente]") | H9: =IFERROR(INDEX('Tesis B · 15 targets'!$I$5:$I$19,MATCH(LARGE('Tesis B · 15 targets'!$K$5:$K$19,5),'Tesis B · 15 targets'!$K$5:$K$19,0)),"[SABI pendiente]") | I9: =IFERROR(H9/F9,"n.d.")
B10: Total 5 adquisiciones | F10: =SUM(F5:F9) | H10: =SUM(H5:H9) | I10: =IFERROR(H10/F10,"n.d.")
B11: Psyma Ibérica hoy | F11: =Supuestos!B3 | H11: =Supuestos!B4 | I11: =IFERROR(H11/F11,"n.d.")
B12: Psyma + 5 targets (proforma) | F12: =F10+F11 | H12: =H10+H11 | I12: =IFERROR(H12/F12,"n.d.")
B13: Multiplicador de EBITDA vs Psyma hoy | H13: =IFERROR(H12/H11,"n.d.")
B15: Selección automática: las 5 empresas de la lista de 15 con mayor EBITDA positivo. Si cambias un dato en la lista de 15, el top 5 se recalcula.

Sheet Tesis A · Top 5
A1: Tesis A · Top 5 que maximiza el EV (última lámina)
A2: Se rellena solo al introducir ventas y EBITDA de SABI en la hoja «Tesis A · 15 targets».
A4: # | B4: Empresa | C4: Vertical | D4: Descripción de servicios | E4: Especialización | F4: Ingresos (k€) | G4: Año dato | H4: EBITDA (k€) | I4: Margen EBITDA
A5: 1 | B5: =IFERROR(INDEX('Tesis A · 15 targets'!$B$5:$B$19,MATCH(LARGE('Tesis A · 15 targets'!$K$5:$K$19,1),'Tesis A · 15 targets'!$K$5:$K$19,0)),"[SABI pendiente]") | C5: =IFERROR(INDEX('Tesis A · 15 targets'!$C$5:$C$19,MATCH(LARGE('Tesis A · 15 targets'!$K$5:$K$19,1),'Tesis A · 15 targets'!$K$5:$K$19,0)),"[SABI pendiente]") | D5: =IFERROR(INDEX('Tesis A · 15 targets'!$D$5:$D$19,MATCH(LARGE('Tesis A · 15 targets'!$K$5:$K$19,1),'Tesis A · 15 targets'!$K$5:$K$19,0)),"[SABI pendiente]") | E5: =IFERROR(INDEX('Tesis A · 15 targets'!$E$5:$E$19,MATCH(LARGE('Tesis A · 15 targets'!$K$5:$K$19,1),'Tesis A · 15 targets'!$K$5:$K$19,0)),"[SABI pendiente]") | F5: =IFERROR(INDEX('Tesis A · 15 targets'!$G$5:$G$19,MATCH(LARGE('Tesis A · 15 targets'!$K$5:$K$19,1),'Tesis A · 15 targets'!$K$5:$K$19,0)),"[SABI pendiente]") | G5: =IFERROR(INDEX('Tesis A · 15 targets'!$H$5:$H$19,MATCH(LARGE('Tesis A · 15 targets'!$K$5:$K$19,1),'Tesis A · 15 targets'!$K$5:$K$19,0)),"[SABI pendiente]") | H5: =IFERROR(INDEX('Tesis A · 15 targets'!$I$5:$I$19,MATCH(LARGE('Tesis A · 15 targets'!$K$5:$K$19,1),'Tesis A · 15 targets'!$K$5:$K$19,0)),"[SABI pendiente]") | I5: =IFERROR(H5/F5,"n.d.")
A6: 2 | B6: =IFERROR(INDEX('Tesis A · 15 targets'!$B$5:$B$19,MATCH(LARGE('Tesis A · 15 targets'!$K$5:$K$19,2),'Tesis A · 15 targets'!$K$5:$K$19,0)),"[SABI pendiente]") | C6: =IFERROR(INDEX('Tesis A · 15 targets'!$C$5:$C$19,MATCH(LARGE('Tesis A · 15 targets'!$K$5:$K$19,2),'Tesis A · 15 targets'!$K$5:$K$19,0)),"[SABI pendiente]") | D6: =IFERROR(INDEX('Tesis A · 15 targets'!$D$5:$D$19,MATCH(LARGE('Tesis A · 15 targets'!$K$5:$K$19,2),'Tesis A · 15 targets'!$K$5:$K$19,0)),"[SABI pendiente]") | E6: =IFERROR(INDEX('Tesis A · 15 targets'!$E$5:$E$19,MATCH(LARGE('Tesis A · 15 targets'!$K$5:$K$19,2),'Tesis A · 15 targets'!$K$5:$K$19,0)),"[SABI pendiente]") | F6: =IFERROR(INDEX('Tesis A · 15 targets'!$G$5:$G$19,MATCH(LARGE('Tesis A · 15 targets'!$K$5:$K$19,2),'Tesis A · 15 targets'!$K$5:$K$19,0)),"[SABI pendiente]") | G6: =IFERROR(INDEX('Tesis A · 15 targets'!$H$5:$H$19,MATCH(LARGE('Tesis A · 15 targets'!$K$5:$K$19,2),'Tesis A · 15 targets'!$K$5:$K$19,0)),"[SABI pendiente]") | H6: =IFERROR(INDEX('Tesis A · 15 targets'!$I$5:$I$19,MATCH(LARGE('Tesis A · 15 targets'!$K$5:$K$19,2),'Tesis A · 15 targets'!$K$5:$K$19,0)),"[SABI pendiente]") | I6: =IFERROR(H6/F6,"n.d.")
A7: 3 | B7: =IFERROR(INDEX('Tesis A · 15 targets'!$B$5:$B$19,MATCH(LARGE('Tesis A · 15 targets'!$K$5:$K$19,3),'Tesis A · 15 targets'!$K$5:$K$19,0)),"[SABI pendiente]") | C7: =IFERROR(INDEX('Tesis A · 15 targets'!$C$5:$C$19,MATCH(LARGE('Tesis A · 15 targets'!$K$5:$K$19,3),'Tesis A · 15 targets'!$K$5:$K$19,0)),"[SABI pendiente]") | D7: =IFERROR(INDEX('Tesis A · 15 targets'!$D$5:$D$19,MATCH(LARGE('Tesis A · 15 targets'!$K$5:$K$19,3),'Tesis A · 15 targets'!$K$5:$K$19,0)),"[SABI pendiente]") | E7: =IFERROR(INDEX('Tesis A · 15 targets'!$E$5:$E$19,MATCH(LARGE('Tesis A · 15 targets'!$K$5:$K$19,3),'Tesis A · 15 targets'!$K$5:$K$19,0)),"[SABI pendiente]") | F7: =IFERROR(INDEX('Tesis A · 15 targets'!$G$5:$G$19,MATCH(LARGE('Tesis A · 15 targets'!$K$5:$K$19,3),'Tesis A · 15 targets'!$K$5:$K$19,0)),"[SABI pendiente]") | G7: =IFERROR(INDEX('Tesis A · 15 targets'!$H$5:$H$19,MATCH(LARGE('Tesis A · 15 targets'!$K$5:$K$19,3),'Tesis A · 15 targets'!$K$5:$K$19,0)),"[SABI pendiente]") | H7: =IFERROR(INDEX('Tesis A · 15 targets'!$I$5:$I$19,MATCH(LARGE('Tesis A · 15 targets'!$K$5:$K$19,3),'Tesis A · 15 targets'!$K$5:$K$19,0)),"[SABI pendiente]") | I7: =IFERROR(H7/F7,"n.d.")
A8: 4 | B8: =IFERROR(INDEX('Tesis A · 15 targets'!$B$5:$B$19,MATCH(LARGE('Tesis A · 15 targets'!$K$5:$K$19,4),'Tesis A · 15 targets'!$K$5:$K$19,0)),"[SABI pendiente]") | C8: =IFERROR(INDEX('Tesis A · 15 targets'!$C$5:$C$19,MATCH(LARGE('Tesis A · 15 targets'!$K$5:$K$19,4),'Tesis A · 15 targets'!$K$5:$K$19,0)),"[SABI pendiente]") | D8: =IFERROR(INDEX('Tesis A · 15 targets'!$D$5:$D$19,MATCH(LARGE('Tesis A · 15 targets'!$K$5:$K$19,4),'Tesis A · 15 targets'!$K$5:$K$19,0)),"[SABI pendiente]") | E8: =IFERROR(INDEX('Tesis A · 15 targets'!$E$5:$E$19,MATCH(LARGE('Tesis A · 15 targets'!$K$5:$K$19,4),'Tesis A · 15 targets'!$K$5:$K$19,0)),"[SABI pendiente]") | F8: =IFERROR(INDEX('Tesis A · 15 targets'!$G$5:$G$19,MATCH(LARGE('Tesis A · 15 targets'!$K$5:$K$19,4),'Tesis A · 15 targets'!$K$5:$K$19,0)),"[SABI pendiente]") | G8: =IFERROR(INDEX('Tesis A · 15 targets'!$H$5:$H$19,MATCH(LARGE('Tesis A · 15 targets'!$K$5:$K$19,4),'Tesis A · 15 targets'!$K$5:$K$19,0)),"[SABI pendiente]") | H8: =IFERROR(INDEX('Tesis A · 15 targets'!$I$5:$I$19,MATCH(LARGE('Tesis A · 15 targets'!$K$5:$K$19,4),'Tesis A · 15 targets'!$K$5:$K$19,0)),"[SABI pendiente]") | I8: =IFERROR(H8/F8,"n.d.")
A9: 5 | B9: =IFERROR(INDEX('Tesis A · 15 targets'!$B$5:$B$19,MATCH(LARGE('Tesis A · 15 targets'!$K$5:$K$19,5),'Tesis A · 15 targets'!$K$5:$K$19,0)),"[SABI pendiente]") | C9: =IFERROR(INDEX('Tesis A · 15 targets'!$C$5:$C$19,MATCH(LARGE('Tesis A · 15 targets'!$K$5:$K$19,5),'Tesis A · 15 targets'!$K$5:$K$19,0)),"[SABI pendiente]") | D9: =IFERROR(INDEX('Tesis A · 15 targets'!$D$5:$D$19,MATCH(LARGE('Tesis A · 15 targets'!$K$5:$K$19,5),'Tesis A · 15 targets'!$K$5:$K$19,0)),"[SABI pendiente]") | E9: =IFERROR(INDEX('Tesis A · 15 targets'!$E$5:$E$19,MATCH(LARGE('Tesis A · 15 targets'!$K$5:$K$19,5),'Tesis A · 15 targets'!$K$5:$K$19,0)),"[SABI pendiente]") | F9: =IFERROR(INDEX('Tesis A · 15 targets'!$G$5:$G$19,MATCH(LARGE('Tesis A · 15 targets'!$K$5:$K$19,5),'Tesis A · 15 targets'!$K$5:$K$19,0)),"[SABI pendiente]") | G9: =IFERROR(INDEX('Tesis A · 15 targets'!$H$5:$H$19,MATCH(LARGE('Tesis A · 15 targets'!$K$5:$K$19,5),'Tesis A · 15 targets'!$K$5:$K$19,0)),"[SABI pendiente]") | H9: =IFERROR(INDEX('Tesis A · 15 targets'!$I$5:$I$19,MATCH(LARGE('Tesis A · 15 targets'!$K$5:$K$19,5),'Tesis A · 15 targets'!$K$5:$K$19,0)),"[SABI pendiente]") | I9: =IFERROR(H9/F9,"n.d.")
B10: Total 5 adquisiciones | F10: =SUM(F5:F9) | H10: =SUM(H5:H9) | I10: =IFERROR(H10/F10,"n.d.")
B11: Psyma Ibérica hoy | F11: =Supuestos!B3 | H11: =Supuestos!B4 | I11: =IFERROR(H11/F11,"n.d.")
B12: Psyma + 5 targets (proforma) | F12: =F10+F11 | H12: =H10+H11 | I12: =IFERROR(H12/F12,"n.d.")
B13: Multiplicador de EBITDA vs Psyma hoy | H13: =IFERROR(H12/H11,"n.d.")
B15: Selección automática: las 5 empresas de la lista de 15 con mayor EBITDA positivo. Si cambias un dato en la lista de 15, el top 5 se recalcula.

Sheet Supuestos
A1: Supuestos
A3: Psyma Ibérica · Ventas 2024 (k€) | B3: 3789 | C3: Fuente: SABI (tabla de mercado de investigación pharma facilitada por el usuario)
A4: Psyma Ibérica · EBITDA 2024 (k€) | B4: 39 | C4: Fuente: SABI (tabla de mercado de investigación pharma facilitada por el usuario)
A6: Criterio de ranking | B6: Aportación de EBITDA: con múltiplo constante, más EBITDA = más EV. Empresas sin dato o con EBITDA negativo no entran en el top 5.
