Workbook

Sheet Tesis A · 15 targets
A1: Tesis A · 15 targets por capa de la cadena de valor pharma (penúltima lámina)
A2: Sin investigación de mercados. Origen: cribado de la Tesis A. Amarillo = completar con SABI. Negro = fórmula.
A4: # | B4: Empresa | C4: Capa (vertical) | D4: Descripción de servicios | E4: Accionista / sede | F4: Encaje con la tesis | G4: Paso del build-up | H4: Confianza | I4: Ingresos (k€) | J4: Año dato | K4: EBITDA (k€) | L4: Margen EBITDA | M4: Origen
A5: 1 | B5: Hygeia Consulting | C5: 2 · Estrategia y consultoría | D5: Consultoría e investigación aplicada en gestión y evaluación de servicios y políticas sanitarias | E5: Independiente (verificar) · Madrid | F5: Del dato a la recomendación estratégica en salud | G5: Paso 1 | H5: Media | L5: =IF(AND(ISNUMBER(I5),ISNUMBER(K5),I5<>0),K5/I5,"n.d.") | M5: Cribado Tesis A · Shortlist
A6: 2 | B6: Luzán 5 Health Consulting | C6: 2 · Estrategia y consultoría | D6: Consultoría en salud y formación; empresa familiar desde 1982 | E6: Familiar · Madrid | F6: Consultoría + formación médica: cubre las capas 2 y 5 | G6: Paso 1 (o 3) | H6: Alta | L6: =IF(AND(ISNUMBER(I6),ISNUMBER(K6),I6<>0),K6/I6,"n.d.") | M6: Cribado Tesis A · Shortlist
A7: 3 | B7: Mediformplus | C7: 2 · Estrategia y consultoría | D7: Formación y apoyo a la industria farmacéutica en estrategia comercial y trade marketing | E7: Independiente (verificar) · España (verificar) | F7: Estrategia comercial pharma; tamaño por confirmar | G7: Paso 1 | H7: Baja | L7: =IF(AND(ISNUMBER(I7),ISNUMBER(K7),I7<>0),K7/I7,"n.d.") | M7: Cribado Tesis A · Reserva
A8: 4 | B8: PORIB (Pharmacoeconomics & Outcomes Research Iberia) | C8: 3 · Evidencia (HEOR y RWE) | D8: HEOR, bioestadística, economía de la salud, market access y comunicación de resultados; fundada en 2004 | E8: Independiente (empresa propia) · Pozuelo de Alarcón (Madrid) | F8: Evidencia + acceso en un solo paso | G8: Paso 2 | H8: Alta | L8: =IF(AND(ISNUMBER(I8),ISNUMBER(K8),I8<>0),K8/I8,"n.d.") | M8: Cribado Tesis A · Shortlist
A9: 5 | B9: Axentiva Solutions | C9: 3 · Evidencia (HEOR y RWE) | D9: HEOR y market access; Top 10 HEOR Europa 2023 | E9: Fundador (Carlos Crespo) · Barcelona | F9: Modelización HEOR con equipo académico | G9: Paso 2 | H9: Alta | L9: =IF(AND(ISNUMBER(I9),ISNUMBER(K9),I9<>0),K9/I9,"n.d.") | M9: Cribado Tesis A · Shortlist
A10: 6 | B10: OXON Epidemiology | C10: 3 · Evidencia (HEOR y RWE) | D10: CRO de RWE: estudios observacionales, farmacoepidemiología, HEOR; centro ENCePP | E10: Verificar (posible vínculo con Syneos) · Madrid / Londres | F10: Aporta RWE, la parte que más crece | G10: Paso 2 | H10: Media | L10: =IF(AND(ISNUMBER(I10),ISNUMBER(K10),I10<>0),K10/I10,"n.d.") | M10: Cribado Tesis A · Shortlist
A11: 7 | B11: Get Access Consulting | C11: 4 · Acceso y pricing | D11: Precio y reembolso, acceso temprano y market access regional; oncología, hospital y enfermedades raras | E11: Independiente (verificar) · España (verificar sede) | F11: Acceso y precio: se vende junto a la evidencia | G11: Paso 2 | H11: Media | L11: =IF(AND(ISNUMBER(I11),ISNUMBER(K11),I11<>0),K11/I11,"n.d.") | M11: Cribado Tesis A · Shortlist
A12: 8 | B12: RCAPharma | C12: 4 · Acceso y pricing | D12: Asesoría regulatoria, farmacovigilancia y acceso al mercado; fundada en 1991 | E12: Independiente (verificar) · Madrid | F12: Acceso + regulatorio con cartera de laboratorios | G12: Paso 2 | H12: Media | L12: =IF(AND(ISNUMBER(I12),ISNUMBER(K12),I12<>0),K12/I12,"n.d.") | M12: Cribado Tesis A · Shortlist
A13: 9 | B13: Ergon | C13: 5 · Comunicación médica | D13: Comunicación médica y edición científica para la industria farmacéutica; +30 años | E13: Independiente (verificar) · Madrid | F13: Contenido científico y relación con sociedades médicas | G13: Paso 3 | H13: Media | L13: =IF(AND(ISNUMBER(I13),ISNUMBER(K13),I13<>0),K13/I13,"n.d.") | M13: Cribado Tesis A · Shortlist
A14: 10 | B14: Doctaforum | C14: 5 · Comunicación médica | D14: Comunicación en salud, consultoría científica y eventos médicos; +50 empleados | E14: Independiente (verificar) · Madrid | F14: Eventos y congresos: ingreso recurrente tras el lanzamiento | G14: Paso 3 | H14: Media | L14: =IF(AND(ISNUMBER(I14),ISNUMBER(K14),I14<>0),K14/I14,"n.d.") | M14: Cribado Tesis A · Shortlist
A15: 11 | B15: Content Ed Net | C15: 5 · Comunicación médica | D15: Redacción médica y comunicación científica | E15: Verificar · Madrid | F15: Medical writing para lanzamientos | G15: Paso 3 | H15: Media | L15: =IF(AND(ISNUMBER(I15),ISNUMBER(K15),I15<>0),K15/I15,"n.d.") | M15: Cribado Tesis A · Shortlist
A16: 12 | B16: Pulso Ediciones | C16: 5 · Comunicación médica | D16: Formación médica continuada y edición; fundada en 1979 | E16: Verificar · Barcelona | F16: Formación médica continuada acreditada | G16: Paso 3 | H16: Media | L16: =IF(AND(ISNUMBER(I16),ISNUMBER(K16),I16<>0),K16/I16,"n.d.") | M16: Cribado Tesis A · Shortlist
... A19: 15 | B19: Esmon Pharma | C19: 5 · Comunicación médica | D19: Editorial y comunicación médica | E19: Verificar · España (verificar) | F19: Completa la capa de comunicación médica | G19: Paso 3 | H19: Baja | L19: =IF(AND(ISNUMBER(I19),ISNUMBER(K19),I19<>0),K19/I19,"n.d.") | M19: Añadida para completar 15
B21: Distribución por capa
B22: Capa | C22: Nº empresas
B23: 2 · Estrategia y consultoría | C23: =COUNTIF($C$5:$C$19,B23)
B24: 3 · Evidencia (HEOR y RWE) | C24: =COUNTIF($C$5:$C$19,B24)
B25: 4 · Acceso y pricing | C25: =COUNTIF($C$5:$C$19,B25)
B26: 5 · Comunicación médica | C26: =COUNTIF($C$5:$C$19,B26)
B27: Total | C27: =SUM(C23:C26)

Sheet Tesis A · Top 5
A1: Tesis A · Top 5 que maximiza el EV (última lámina)
A2: Criterio: una empresa por capa (2, 3, 4 y 5) + una segunda en evidencia. La tesis A sube el múltiplo al completar las capas («mismo cliente, más capas, mayor múltiplo»). Cifras enlazadas a la hoja de 15: se rellenan al meter SABI.
A4: # | B4: Empresa | C4: Capa (vertical) | D4: Por qué entra | E4: Ingresos (k€) | F4: Año dato | G4: EBITDA (k€) | H4: Margen EBITDA
A5: 1 | B5: Luzán 5 Health Consulting | C5: =INDEX('Tesis A · 15 targets'!$C$5:$C$19,MATCH(B5,'Tesis A · 15 targets'!$B$5:$B$19,0)) | D5: Paso 1: consultoría + formación médica; empresa familiar desde 1982 (posible sucesión) | E5: =IF(ISNUMBER(INDEX('Tesis A · 15 targets'!$I$5:$I$19,MATCH(B5,'Tesis A · 15 targets'!$B$5:$B$19,0))),INDEX('Tesis A · 15 targets'!$I$5:$I$19,MATCH(B5,'Tesis A · 15 targets'!$B$5:$B$19,0)),"[SABI]") | F5: =IF(INDEX('Tesis A · 15 targets'!$J$5:$J$19,MATCH(B5,'Tesis A · 15 targets'!$B$5:$B$19,0))="","[SABI]",INDEX('Tesis A · 15 targets'!$J$5:$J$19,MATCH(B5,'Tesis A · 15 targets'!$B$5:$B$19,0))) | G5: =IF(ISNUMBER(INDEX('Tesis A · 15 targets'!$K$5:$K$19,MATCH(B5,'Tesis A · 15 targets'!$B$5:$B$19,0))),INDEX('Tesis A · 15 targets'!$K$5:$K$19,MATCH(B5,'Tesis A · 15 targets'!$B$5:$B$19,0)),"[SABI]") | H5: =IFERROR(G5/E5,"n.d.")
A6: 2 | B6: PORIB (Pharmacoeconomics & Outcomes Research Iberia) | C6: =INDEX('Tesis A · 15 targets'!$C$5:$C$19,MATCH(B6,'Tesis A · 15 targets'!$B$5:$B$19,0)) | D6: Paso 2: HEOR y market access en una sola compra; independiente desde 2004 | E6: =IF(ISNUMBER(INDEX('Tesis A · 15 targets'!$I$5:$I$19,MATCH(B6,'Tesis A · 15 targets'!$B$5:$B$19,0))),INDEX('Tesis A · 15 targets'!$I$5:$I$19,MATCH(B6,'Tesis A · 15 targets'!$B$5:$B$19,0)),"[SABI]") | F6: =IF(INDEX('Tesis A · 15 targets'!$J$5:$J$19,MATCH(B6,'Tesis A · 15 targets'!$B$5:$B$19,0))="","[SABI]",INDEX('Tesis A · 15 targets'!$J$5:$J$19,MATCH(B6,'Tesis A · 15 targets'!$B$5:$B$19,0))) | G6: =IF(ISNUMBER(INDEX('Tesis A · 15 targets'!$K$5:$K$19,MATCH(B6,'Tesis A · 15 targets'!$B$5:$B$19,0))),INDEX('Tesis A · 15 targets'!$K$5:$K$19,MATCH(B6,'Tesis A · 15 targets'!$B$5:$B$19,0)),"[SABI]") | H6: =IFERROR(G6/E6,"n.d.")
A7: 3 | B7: Axentiva Solutions | C7: =INDEX('Tesis A · 15 targets'!$C$5:$C$19,MATCH(B7,'Tesis A · 15 targets'!$B$5:$B$19,0)) | D7: Paso 2: modelización HEOR; la evidencia es la capa que más crece | E7: =IF(ISNUMBER(INDEX('Tesis A · 15 targets'!$I$5:$I$19,MATCH(B7,'Tesis A · 15 targets'!$B$5:$B$19,0))),INDEX('Tesis A · 15 targets'!$I$5:$I$19,MATCH(B7,'Tesis A · 15 targets'!$B$5:$B$19,0)),"[SABI]") | F7: =IF(INDEX('Tesis A · 15 targets'!$J$5:$J$19,MATCH(B7,'Tesis A · 15 targets'!$B$5:$B$19,0))="","[SABI]",INDEX('Tesis A · 15 targets'!$J$5:$J$19,MATCH(B7,'Tesis A · 15 targets'!$B$5:$B$19,0))) | G7: =IF(ISNUMBER(INDEX('Tesis A · 15 targets'!$K$5:$K$19,MATCH(B7,'Tesis A · 15 targets'!$B$5:$B$19,0))),INDEX('Tesis A · 15 targets'!$K$5:$K$19,MATCH(B7,'Tesis A · 15 targets'!$B$5:$B$19,0)),"[SABI]") | H7: =IFERROR(G7/E7,"n.d.")
A8: 4 | B8: Get Access Consulting | C8: =INDEX('Tesis A · 15 targets'!$C$5:$C$19,MATCH(B8,'Tesis A · 15 targets'!$B$5:$B$19,0)) | D8: Paso 2: precio, reembolso y acceso temprano; se vende junto a la evidencia | E8: =IF(ISNUMBER(INDEX('Tesis A · 15 targets'!$I$5:$I$19,MATCH(B8,'Tesis A · 15 targets'!$B$5:$B$19,0))),INDEX('Tesis A · 15 targets'!$I$5:$I$19,MATCH(B8,'Tesis A · 15 targets'!$B$5:$B$19,0)),"[SABI]") | F8: =IF(INDEX('Tesis A · 15 targets'!$J$5:$J$19,MATCH(B8,'Tesis A · 15 targets'!$B$5:$B$19,0))="","[SABI]",INDEX('Tesis A · 15 targets'!$J$5:$J$19,MATCH(B8,'Tesis A · 15 targets'!$B$5:$B$19,0))) | G8: =IF(ISNUMBER(INDEX('Tesis A · 15 targets'!$K$5:$K$19,MATCH(B8,'Tesis A · 15 targets'!$B$5:$B$19,0))),INDEX('Tesis A · 15 targets'!$K$5:$K$19,MATCH(B8,'Tesis A · 15 targets'!$B$5:$B$19,0)),"[SABI]") | H8: =IFERROR(G8/E8,"n.d.")
A9: 5 | B9: Doctaforum | C9: =INDEX('Tesis A · 15 targets'!$C$5:$C$19,MATCH(B9,'Tesis A · 15 targets'!$B$5:$B$19,0)) | D9: Paso 3: eventos y congresos médicos; recurrencia tras el lanzamiento; +50 empleados | E9: =IF(ISNUMBER(INDEX('Tesis A · 15 targets'!$I$5:$I$19,MATCH(B9,'Tesis A · 15 targets'!$B$5:$B$19,0))),INDEX('Tesis A · 15 targets'!$I$5:$I$19,MATCH(B9,'Tesis A · 15 targets'!$B$5:$B$19,0)),"[SABI]") | F9: =IF(INDEX('Tesis A · 15 targets'!$J$5:$J$19,MATCH(B9,'Tesis A · 15 targets'!$B$5:$B$19,0))="","[SABI]",INDEX('Tesis A · 15 targets'!$J$5:$J$19,MATCH(B9,'Tesis A · 15 targets'!$B$5:$B$19,0))) | G9: =IF(ISNUMBER(INDEX('Tesis A · 15 targets'!$K$5:$K$19,MATCH(B9,'Tesis A · 15 targets'!$B$5:$B$19,0))),INDEX('Tesis A · 15 targets'!$K$5:$K$19,MATCH(B9,'Tesis A · 15 targets'!$B$5:$B$19,0)),"[SABI]") | H9: =IFERROR(G9/E9,"n.d.")
B11: Total 5 adquisiciones | E11: =SUM(E5:E9) | G11: =SUM(G5:G9) | H11: =IFERROR(G11/E11,"n.d.")
B12: Psyma Ibérica hoy (SABI 2024) | E12: 3789 | G12: 39 | H12: =IFERROR(G12/E12,"n.d.")
B13: Psyma + 5 targets (proforma) | E13: =E11+E12 | G13: =G11+G12 | H13: =IFERROR(G13/E13,"n.d.")
B15: Reservas si alguna no tiene cuentas en SABI: Hygeia Consulting (capa 2), OXON Epidemiology (capa 3), RCAPharma (capa 4), Ergon (capa 5). Cambia el nombre en la columna B y todo se recalcula.
