Workbook

Sheet Cribado Tesis A
A1: Psyma Ibérica · Tesis A · Cribado de add-ons por capa de la cadena de valor pharma (España)
A2: Criterio add-on: empresa española, independiente (sin grupo, multinacional ni PE) y con cuentas en SABI. Amarillo = completar con SABI. «Ya consolidada» = precedente de la tesis, no disponible.
A4: Capa (vertical) | B4: Empresa | C4: Sede | D4: Actividad | E4: Propiedad | F4: Estado | G4: Encaje / motivo | H4: Paso del build-up | I4: Confianza del dato | J4: Ventas 2024 (M€) | K4: EBITDA 2024 (M€) | L4: Empleados | M4: ¿Cuentas en SABI? (Sí/No) | N4: Fuente
A5: 1 · Investigación de mercados pharma | B5: Core Research | C5: España (verificar sede) | D5: Instituto de investigación de mercados de referencia en pharma, +20 años | E5: 100% capital nacional | F5: Shortlist | G5: Consolidación horizontal: mismo cliente y mismo servicio que Psyma | H5: Consolidación horizontal | I5: Media | N5: pmfarma.com/empresas/E4578-core-research
A6: 1 · Investigación de mercados pharma | B6: Pharmore Research | C6: Barcelona | D6: Investigación full-service y campo, 100% pharma y salud; fundada en 2002 | E6: Independiente | F6: Shortlist | G6: Añade campo propio y presencia en Barcelona | H6: Consolidación horizontal | I6: Alta | N6: pharmoreresearch.com
A7: 1 · Investigación de mercados pharma | B7: Fesdex | C7: Barcelona | D7: Estudios de mercado para la industria farmacéutica en España e Italia | E7: Independiente (verificar) | F7: Shortlist | G7: Cartera pharma y entrada en Italia | H7: Consolidación horizontal | I7: Media | N7: fesdex.es
A8: 1 · Investigación de mercados pharma | B8: IVP Iberica | C8: Madrid / Barcelona | D8: Campo healthcare con panel fidelizado de +15.000 médicos y salas propias | E8: Red Inter-View Partners (verificar si hay participación) | F8: Shortlist | G8: Panel de médicos propio: abarata el campo de Psyma | H8: Consolidación horizontal | I8: Media | N8: ephmra.org/supplier-directory/586
A9: 1 · Investigación de mercados pharma | B9: IEXP · Instituto para la Experiencia del Paciente | C9: Madrid (verificar) | D9: Medición y consultoría de experiencia de paciente para hospitales y laboratorios (Novartis, GSK, Leo Pharma) | E9: Independiente (verificar) | F9: Shortlist | G9: Abre la voz del paciente; también en la shortlist de la tesis B | H9: Consolidación horizontal | I9: Media | N9: iexp.es/laboratorios
A10: 1 · Investigación de mercados pharma | B10: Amber Marketing | C10: España | D10: Investigación de mercados en salud | E10: Minerva Insights (Ufenau), 2023 | F10: Ya consolidada (precedente) | G10: Ya comprada: precedente de consolidación | H10: — | I10: Alta | N10: webcapitalriesgo.com
A11: 1 · Investigación de mercados pharma | B11: IQVIA / Ipsos Healthcare / Cerner Enviza | C11: Madrid | D11: Dato y research pharma | E11: Multinacionales | F11: Descartada | G11: No es add-on: multinacionales | H11: — | I11: Alta
A12: 2 · Estrategia y consultoría | B12: Hygeia Consulting | C12: Madrid | D12: Consultoría e investigación aplicada en gestión y evaluación de servicios y políticas sanitarias | E12: Independiente (verificar) | F12: Shortlist | G12: Del dato a la recomendación estratégica en salud | H12: Paso 1 | I12: Media | N12: hygeiaconsulting.com
A13: 2 · Estrategia y consultoría | B13: Luzán 5 Health Consulting | C13: Madrid | D13: Consultoría en salud y formación; empresa familiar desde 1982 | E13: Familiar | F13: Shortlist | G13: Consultoría + formación médica: cubre las capas 2 y 5 | H13: Paso 1 (o 3) | I13: Alta | N13: luzan5.com
A14: 2 · Estrategia y consultoría | B14: Mediformplus | C14: España (verificar) | D14: Formación y apoyo a la industria farmacéutica en estrategia comercial y trade marketing | E14: Independiente (verificar) | F14: Reserva | G14: Estrategia comercial pharma; tamaño por confirmar | H14: Paso 1 | I14: Baja | N14: pharmatech.es
A15: 2 · Estrategia y consultoría | B15: Salvetti & Llombart | C15: Barcelona | D15: Consultoría estratégica e insights | E15: Minerva Insights (Ufenau), 2023 | F15: Ya consolidada (precedente) | G15: Ya comprada: precedente | H15: — | I15: Alta | N15: webcapitalriesgo.com
A16: 2 · Estrategia y consultoría | B16: Antares Consulting | C16: Barcelona / Madrid | D16: Consultoría de estrategia y gestión en salud y life sciences | E16: No independiente (Evidenze; antes Grupo Catalana Occidente) | F16: Ya consolidada (precedente) | G16: Ya integrada en un grupo | H16: — | I16: Media | N16: einforma.com (Antares Evidenze Consulting SL)
A17: 2 · Estrategia y consultoría | B17: Ascendo Sanidad&Farma | C17: Madrid | D17: Consultoría estratégica en salud | E17: Sociedad extinguida | F17: Descartada | G17: Ya no opera | H17: — | I17: Alta | N17: iberinform.es
A18: 3 · Evidencia (HEOR y RWE) | B18: PORIB (Pharmacoeconomics & Outcomes Research Iberia) | C18: Pozuelo de Alarcón (Madrid) | D18: HEOR, bioestadística, economía de la salud, market access y comunicación de resultados; fundada en 2004 | E18: Independiente (empresa propia) | F18: Shortlist | G18: Evidencia + acceso en un solo paso | H18: Paso 2 | I18: Alta | N18: porib.com
A19: 3 · Evidencia (HEOR y RWE) | B19: Axentiva Solutions | C19: Barcelona | D19: HEOR y market access; Top 10 HEOR Europa 2023 | E19: Fundador (Carlos Crespo) | F19: Shortlist | G19: Modelización HEOR con equipo académico | H19: Paso 2 | I19: Alta | N19: axentiva.com
A20: 3 · Evidencia (HEOR y RWE) | B20: OXON Epidemiology | C20: Madrid / Londres | D20: CRO de RWE: estudios observacionales, farmacoepidemiología, HEOR; centro ENCePP | E20: Verificar (posible vínculo con Syneos) | F20: Shortlist | G20: Aporta RWE, la parte que más crece | H20: Paso 2 | I20: Media | N20: oxonepi.com
A21: 3 · Evidencia (HEOR y RWE) | B21: Oblikue Consulting | C21: Barcelona | D21: HEOR y market access | E21: PharmaLex (hoy Cencora), 2021 | F21: Ya consolidada (precedente) | G21: Ya comprada: precedente | H21: — | I21: Alta | N21: pharmalex.com
A22: 3 · Evidencia (HEOR y RWE) | B22: Weber Economía y Salud | C22: Madrid | D22: HEOR, evaluación de tecnologías sanitarias y market access | E22: Vivactis Group, 2023 | F22: Ya consolidada (precedente) | G22: Ya comprada: precedente | H22: — | I22: Alta | N22: weber.org.es
A23: 3 · Evidencia (HEOR y RWE) | B23: Outcomes'10 | C23: Castellón | D23: Resultados en salud, economía de la salud y market access | E23: ProductLife Group | F23: Ya consolidada (precedente) | G23: Ya comprada: precedente | H23: — | I23: Alta | N23: linkedin.com/company/outcomes10
... A33: 5 · Comunicación médica | B33: Grupo SANED | C33: Madrid | D33: Comunicación científica y educación médica; líder en España | E33: Medscape | F33: Ya consolidada (precedente) | G33: Ya comprada: precedente | H33: — | I33: Alta | N33: forbes.es

Sheet Resumen
A1: Resumen por capa
A3: Capa | B3: Shortlist | C3: Reserva | D3: Ya consolidadas (precedentes) | E3: Ventas shortlist (M€)
A4: 1 · Investigación de mercados pharma | B4: =COUNTIFS('Cribado Tesis A'!$A$5:$A$33,A4,'Cribado Tesis A'!$F$5:$F$33,"Shortlist") | C4: =COUNTIFS('Cribado Tesis A'!$A$5:$A$33,A4,'Cribado Tesis A'!$F$5:$F$33,"Reserva") | D4: =COUNTIFS('Cribado Tesis A'!$A$5:$A$33,A4,'Cribado Tesis A'!$F$5:$F$33,"Ya consolidada (precedente)") | E4: =SUMIFS('Cribado Tesis A'!$J$5:$J$33,'Cribado Tesis A'!$A$5:$A$33,A4,'Cribado Tesis A'!$F$5:$F$33,"Shortlist")
A5: 2 · Estrategia y consultoría | B5: =COUNTIFS('Cribado Tesis A'!$A$5:$A$33,A5,'Cribado Tesis A'!$F$5:$F$33,"Shortlist") | C5: =COUNTIFS('Cribado Tesis A'!$A$5:$A$33,A5,'Cribado Tesis A'!$F$5:$F$33,"Reserva") | D5: =COUNTIFS('Cribado Tesis A'!$A$5:$A$33,A5,'Cribado Tesis A'!$F$5:$F$33,"Ya consolidada (precedente)") | E5: =SUMIFS('Cribado Tesis A'!$J$5:$J$33,'Cribado Tesis A'!$A$5:$A$33,A5,'Cribado Tesis A'!$F$5:$F$33,"Shortlist")
A6: 3 · Evidencia (HEOR y RWE) | B6: =COUNTIFS('Cribado Tesis A'!$A$5:$A$33,A6,'Cribado Tesis A'!$F$5:$F$33,"Shortlist") | C6: =COUNTIFS('Cribado Tesis A'!$A$5:$A$33,A6,'Cribado Tesis A'!$F$5:$F$33,"Reserva") | D6: =COUNTIFS('Cribado Tesis A'!$A$5:$A$33,A6,'Cribado Tesis A'!$F$5:$F$33,"Ya consolidada (precedente)") | E6: =SUMIFS('Cribado Tesis A'!$J$5:$J$33,'Cribado Tesis A'!$A$5:$A$33,A6,'Cribado Tesis A'!$F$5:$F$33,"Shortlist")
A7: 4 · Acceso y pricing | B7: =COUNTIFS('Cribado Tesis A'!$A$5:$A$33,A7,'Cribado Tesis A'!$F$5:$F$33,"Shortlist") | C7: =COUNTIFS('Cribado Tesis A'!$A$5:$A$33,A7,'Cribado Tesis A'!$F$5:$F$33,"Reserva") | D7: =COUNTIFS('Cribado Tesis A'!$A$5:$A$33,A7,'Cribado Tesis A'!$F$5:$F$33,"Ya consolidada (precedente)") | E7: =SUMIFS('Cribado Tesis A'!$J$5:$J$33,'Cribado Tesis A'!$A$5:$A$33,A7,'Cribado Tesis A'!$F$5:$F$33,"Shortlist")
A8: 5 · Comunicación médica | B8: =COUNTIFS('Cribado Tesis A'!$A$5:$A$33,A8,'Cribado Tesis A'!$F$5:$F$33,"Shortlist") | C8: =COUNTIFS('Cribado Tesis A'!$A$5:$A$33,A8,'Cribado Tesis A'!$F$5:$F$33,"Reserva") | D8: =COUNTIFS('Cribado Tesis A'!$A$5:$A$33,A8,'Cribado Tesis A'!$F$5:$F$33,"Ya consolidada (precedente)") | E8: =SUMIFS('Cribado Tesis A'!$J$5:$J$33,'Cribado Tesis A'!$A$5:$A$33,A8,'Cribado Tesis A'!$F$5:$F$33,"Shortlist")
A9: Total | B9: =SUM(B4:B8) | C9: =SUM(C4:C8) | D9: =SUM(D4:D8) | E9: =SUM(E4:E8)
A11: Lectura: las capas 3 y 4 ya están en consolidación (Oblikue→PharmaLex, Weber→Vivactis, Outcomes'10→ProductLife, Omakase→G&L) y en comunicación médica SANED→Medscape. Quedan pocas independientes: argumento de urgencia para la tesis A.
